Lab 6/hexTo7Seg.v
module hexTo7Seg(
    input [3:0]x,
    output reg [6:0]z
);
    always @(*)
        case (x)
            4'b0000 : z = 7'b1000000; //hexadecimal 0
            4'b0001 : z = 7'b1111001; //hexadecimal 1
            4'b0010 : z = 7'b0100100; //hexadecimal 2
            4'b0011 : z = 7'b0110000; //hexadecimal 3
            4'b0100 : z = 7'b0011001; //hexadecimal 4
            4'b0101 : z = 7'b0010010; //hexadecimal 5
            4'b0110 : z = 7'b0000010; //hexadecimal 6
            4'b0111 : z = 7'b1111000; //hexadecimal 7
            4'b1000 : z = 7'b0000000; //hexadecimal 8
            4'b1001 : z = 7'b0011000; //hexadecimal 9
            4'b1010 : z = 7'b0001000; //hexadecimal A
            4'b1011 : z = 7'b0000011; //hexadecimal B
            4'b1100 : z = 7'b1000110; //hexadecimal C
            4'b1101 : z = 7'b0100001; //hexadecimal d
            4'b1110 : z = 7'b0000110; //hexadecimal E
            4'b1111 : z = 7'b0001110; //hexadecimal F
            default : z = 7'b1111111; // All segments OFF
        endcase
endmodule

Lab 6/right.v
module right(
    input [3:0] in,       // 4-bit input
    output [3:0] out      // 4-bit output
);

    // LSB is discarded, MSB gets 0
    assign out[3] = in[0];
    assign out[2] = in[3];
    assign out[1] = in[2];
    assign out[0] = in[1];

endmodule

Lab 6/left.v
module left(
    input [3:0] in,       // 4-bit input
    output [3:0] out      // 4-bit output
	 
	);
    // MSB is discarded, LSB gets 0
    assign out[3] = in[2];
    assign out[2] = in[1];
    assign out[1] = in[0];
    assign out[0] = in[3];

endmodule

Lab 6/alu1.v
module alu1 (
    input  A,
    input  B,
    input  Binvert,
    input  Cin,
    input  [1:0] S,   // Operation select
    output R,
    output Cout
);

    // Internal wires
    wire Bx;            
    wire and_out, or_out;
    wire sum, xor1;
    wire and1, and2, and3;
    wire Cout_raw;

    // Invert B 1s comp  
    xor g0(Bx, B, Binvert);

    // AND & OR
    and g1(and_out, A, Bx);
    or  g2(or_out,  A, Bx);

    // Full Adder for ADD/SUB
    xor g3(xor1, A, Bx);
    xor g4(sum, xor1, Cin);
    and g5(and1, A, Bx);
    and g6(and2, A, Cin);
    and g7(and3, Bx, Cin);
    or  g8(Cout_raw, and1, and2, and3);


    // Cout to only ADD/SUB

    wire S_add_sub;
    or u_add_sub(S_add_sub, S[1] & ~S[0], S[1] & S[0]);  // S=10 (ADD) or S=11 (SUB)
    and gCout(Cout, Cout_raw, S_add_sub);                 // Cout valid only for ADD/SUB

    // Mux to select output R
    wire S0_bar, S1_bar;
    wire s_and, s_or, s_add, s_sub;

    not n1(S0_bar, S[0]);
    not n2(S1_bar, S[1]);

    and m1(s_and, and_out, S1_bar, S0_bar);  // AND  S=00
    and m2(s_or,  or_out,  S1_bar, S[0]);    // OR   S=01
    and m3(s_add, sum,     S[1], S0_bar);    // ADD  S=10
    and m4(s_sub, sum,     S[1], S[0]);      // SUB  S=11

    or  m5(R, s_and, s_or, s_add, s_sub);

endmodule

Lab 6/alu2.v
module alu2 (
    input  [1:0] A,    // 2-bit operand A
    input  [1:0] B,    // 2-bit operand B
    input  [2:0] S,    // Operation select (00=AND, 01=OR, 10=ADD, 11=SUB)
    input  Cin,         // Initial carry-in

    output [1:0] R,    // 2-bit result
    output Cout,        // Carry out of MSB
    output c0           // Internal carry from LSB
);

    wire Binvert;

    // Only invert B for SUB (S=011)
    assign Binvert = (S == 3'b011);

    // Bit 0 (LSB)
    alu1 bit0 (
        .A(A[0]),
        .B(B[0]),
        .Binvert(Binvert),
        .Cin(Cin),
        .S(S[1:0]),
        .R(R[0]),
        .Cout(c0)
    );

    // Bit 1 (MSB)
    alu1 bit1 (
        .A(A[1]),
        .B(B[1]),
        .Binvert(Binvert),
        .Cin(c0),
        .S(S[1:0]),
        .R(R[1]),
        .Cout(Cout)
    );

endmodule

Lab 6/alu4.v
module alu4(
    input [3:0] A,
    input [3:0] B,
    input [2:0] S,        // Operation select
    
    output Cout,           // Carry-out of MSB
	 output Overflow,
	 output Zero,
	 
    output [6:0] segR,      // 7-segment display Result
	 output [6:0] segA,      // 7-segment display A
	 output [6:0] segB,       // 7-segment display B
	 output [6:0] segS		// 7-segment display Operation
);

	 wire Binvert, Cin;      // Internal control for ADD/SUB
    wire c;			          // Internal carry wire
	 wire [3:0] aluR;			// Temporary storage for ALU output
	 wire [3:0] shiftL;		// Storage for Rotate Left
	 wire [3:0] shiftR;		// Storage for Rotate Right
	 wire [3:0] R;       	// 4-bit result
	 wire c_mid, c_mid2;
	 
	 
    // Determine Binvert and initial Cin automatically
    assign Binvert = (S == 3'b011);  // Invert B only for SUB
    assign Cin     = (S == 3'b011);  // Cin=1 for SUB, 0 otherwise
	
	// LSB 2-bit ALU
    alu2 lsb (
        .A(A[1:0]),
        .B(B[1:0]),
        .S(S[2:0]),      // Only need 2-bit S for alu2
		  .Cin(Cin),
        .R(aluR[1:0]),
        .Cout(c),
		  .c0(c_mid)
    );

    // MSB 2-bit ALU
    alu2 msb (
        .A(A[3:2]),
        .B(B[3:2]),
        .S(S[2:0]),
		  .Cin(c),
        .R(aluR[3:2]),
        .Cout(Cout),
		  .c0(c_mid2)
    );
	 
	 
	 // Bit shift Left
	 left left(
		.in(A),
		.out(shiftL)
	 );
	 
	 // Bit shift Right
	 right right(
		.in(A),
		.out(shiftR)
	 );
	 
	 // Is less than
	 
	 wire [3:0] slt = (A <   B) ? 4'b0001 : 4'b0000;
	 
	 assign R = (S == 3'b100) ? shiftL :
               (S == 3'b101) ? shiftR :
					(S == 3'b110) ? slt :
               aluR;
					
	 // Overflow detection
	 xor(Overflow, c_mid2, Cout);

	 
	 // Zero Flag Implementation
	 wire r_or1, r_or2, r_or3;

	 or (r_or1, R[3], R[2]);
 	 or (r_or2, R[1], R[0]);
	 or (r_or3, r_or1, r_or2);

	 not (Zero, r_or3);
			 
	 // Convert operands and result to 7-segment displays
    hexTo7Seg displayA (.x(A), .z(segA));
    hexTo7Seg displayB (.x(B), .z(segB));
    hexTo7Seg displayR (.x(R), .z(segR));
	 hexTo7Seg displayS (.x({1'b0,S}), .z(segS));

endmodule

Lab 6/alu4_tb.v
`timescale 1ns/1ps
module alu4_tb;

    reg  [3:0] A, B;
    reg  [2:0] S;
    wire Cout, Overflow, Zero;
    wire [6:0] segR, segA, segB, segS;

    // Add R output (you must expose it in alu4 if not already)
    wire [3:0] R = dut.R;

    // DUT
    alu4 dut(
        .A(A),
        .B(B),
        .S(S),
        .Cout(Cout),
        .Overflow(Overflow),
        .Zero(Zero),
        .segR(segR),
        .segA(segA),
        .segB(segB),
        .segS(segS)
    );

    // Task to print results nicely
    task print_state;
    begin
        $display("Time=%0t  S=%b  A=%b  B=%b  |  R=%b  Cout=%b  OF=%b  Zero=%b",
                 $time, S, A, B, R, Cout, Overflow, Zero);
    end
    endtask

    initial begin
        $dumpfile("alu4_tb.vcd");   // Output VCD file
        $dumpvars(0, alu4_tb);      // Dump all signals in this module
        $display("\n---------------- START ALU4 TEST ----------------\n");

        // ============================
        //        S = 000 (AND)
        // ============================
        S = 3'b000;
        A=4'b0000; B=4'b1111; #10; print_state();
        A=4'b1010; B=4'b1100; #10; print_state();
        A=4'b1111; B=4'b1111; #10; print_state();

        // ============================
        //        S = 001 (OR)
        // ============================
        S = 3'b001;
        A=4'b0000; B=4'b1111; #10; print_state();
        A=4'b1010; B=4'b0101; #10; print_state();
        A=4'b1000; B=4'b0001; #10; print_state();

        // ============================
        //        S = 010 (ADD)
        // ============================
        S = 3'b010;
        A=4'b0001; B=4'b0001; #10; print_state();
        A=4'b0011; B=4'b0101; #10; print_state();   // expect 1000
        A=4'b1111; B=4'b0001; #10; print_state();   // overflow

        // ============================
        //        S = 011 (SUB)
        // ============================
        S = 3'b011;
        A=4'b0100; B=4'b0010; #10; print_state();
        A=4'b0011; B=4'b0101; #10; print_state();
        A=4'b1000; B=4'b0001; #10; print_state();

        // ============================
        //        S = 100 (SHIFT LEFT)
        // ============================
        S = 3'b100;
        B = 4'b0000;
        A=4'b0001; #10; print_state();
        A=4'b1010; #10; print_state();
        A=4'b1111; #10; print_state();

        // ============================
        //        S = 101 (SHIFT RIGHT)
        // ============================
        S = 3'b101;
        B = 4'b0000;
        A=4'b1000; #10; print_state();
        A=4'b1010; #10; print_state();
        A=4'b1111; #10; print_state();

        // ============================
        //        S = 110 (SLT)
        // ============================
        S = 3'b110;
        A=4'b0011; B=4'b0100; #10; print_state();   // A<B = 1
        A=4'b1000; B=4'b0111; #10; print_state();   // signed compare
        A=4'b0100; B=4'b0011; #10; print_state();   // A>B = 0

        $display("\n---------------- END OF TEST ----------------\n");
        $finish;
    end

endmodule

alu4_tb.vcd
$date
	Sat Nov 15 20:15:58 2025
$end
$version
	Icarus Verilog
$end
$timescale
	1ps
$end
$scope module alu4_tb $end
$var wire 4 ! R [3:0] $end
$var wire 7 " segS [6:0] $end
$var wire 7 # segR [6:0] $end
$var wire 7 $ segB [6:0] $end
$var wire 7 % segA [6:0] $end
$var wire 1 & Zero $end
$var wire 1 ' Overflow $end
$var wire 1 ( Cout $end
$var reg 4 ) A [3:0] $end
$var reg 4 * B [3:0] $end
$var reg 3 + S [2:0] $end
$scope module dut $end
$var wire 4 , A [3:0] $end
$var wire 4 - B [3:0] $end
$var wire 1 ' Overflow $end
$var wire 3 . S [2:0] $end
$var wire 1 & Zero $end
$var wire 1 / r_or1 $end
$var wire 1 0 r_or2 $end
$var wire 1 1 r_or3 $end
$var wire 4 2 slt [3:0] $end
$var wire 4 3 shiftR [3:0] $end
$var wire 4 4 shiftL [3:0] $end
$var wire 7 5 segS [6:0] $end
$var wire 7 6 segR [6:0] $end
$var wire 7 7 segB [6:0] $end
$var wire 7 8 segA [6:0] $end
$var wire 1 9 c_mid2 $end
$var wire 1 : c_mid $end
$var wire 1 ; c $end
$var wire 4 < aluR [3:0] $end
$var wire 4 = R [3:0] $end
$var wire 1 ( Cout $end
$var wire 1 > Cin $end
$var wire 1 ? Binvert $end
$scope module displayA $end
$var wire 4 @ x [3:0] $end
$var reg 7 A z [6:0] $end
$upscope $end
$scope module displayB $end
$var wire 4 B x [3:0] $end
$var reg 7 C z [6:0] $end
$upscope $end
$scope module displayR $end
$var wire 4 D x [3:0] $end
$var reg 7 E z [6:0] $end
$upscope $end
$scope module displayS $end
$var wire 4 F x [3:0] $end
$var reg 7 G z [6:0] $end
$upscope $end
$scope module left $end
$var wire 4 H in [3:0] $end
$var wire 4 I out [3:0] $end
$upscope $end
$scope module lsb $end
$var wire 2 J A [1:0] $end
$var wire 2 K B [1:0] $end
$var wire 1 > Cin $end
$var wire 3 L S [2:0] $end
$var wire 1 : c0 $end
$var wire 2 M R [1:0] $end
$var wire 1 ; Cout $end
$var wire 1 N Binvert $end
$scope module bit0 $end
$var wire 1 O A $end
$var wire 1 P B $end
$var wire 1 N Binvert $end
$var wire 1 Q Bx $end
$var wire 1 > Cin $end
$var wire 1 : Cout $end
$var wire 1 R Cout_raw $end
$var wire 1 S R $end
$var wire 2 T S [1:0] $end
$var wire 1 U S0_bar $end
$var wire 1 V S1_bar $end
$var wire 1 W S_add_sub $end
$var wire 1 X and1 $end
$var wire 1 Y and2 $end
$var wire 1 Z and3 $end
$var wire 1 [ and_out $end
$var wire 1 \ or_out $end
$var wire 1 ] s_add $end
$var wire 1 ^ s_and $end
$var wire 1 _ s_or $end
$var wire 1 ` s_sub $end
$var wire 1 a sum $end
$var wire 1 b xor1 $end
$upscope $end
$scope module bit1 $end
$var wire 1 c A $end
$var wire 1 d B $end
$var wire 1 N Binvert $end
$var wire 1 e Bx $end
$var wire 1 : Cin $end
$var wire 1 ; Cout $end
$var wire 1 f Cout_raw $end
$var wire 1 g R $end
$var wire 2 h S [1:0] $end
$var wire 1 i S0_bar $end
$var wire 1 j S1_bar $end
$var wire 1 k S_add_sub $end
$var wire 1 l and1 $end
$var wire 1 m and2 $end
$var wire 1 n and3 $end
$var wire 1 o and_out $end
$var wire 1 p or_out $end
$var wire 1 q s_add $end
$var wire 1 r s_and $end
$var wire 1 s s_or $end
$var wire 1 t s_sub $end
$var wire 1 u sum $end
$var wire 1 v xor1 $end
$upscope $end
$upscope $end
$scope module msb $end
$var wire 2 w A [1:0] $end
$var wire 2 x B [1:0] $end
$var wire 1 ; Cin $end
$var wire 3 y S [2:0] $end
$var wire 1 9 c0 $end
$var wire 2 z R [1:0] $end
$var wire 1 ( Cout $end
$var wire 1 { Binvert $end
$scope module bit0 $end
$var wire 1 | A $end
$var wire 1 } B $end
$var wire 1 { Binvert $end
$var wire 1 ~ Bx $end
$var wire 1 ; Cin $end
$var wire 1 9 Cout $end
$var wire 1 !" Cout_raw $end
$var wire 1 "" R $end
$var wire 2 #" S [1:0] $end
$var wire 1 $" S0_bar $end
$var wire 1 %" S1_bar $end
$var wire 1 &" S_add_sub $end
$var wire 1 '" and1 $end
$var wire 1 (" and2 $end
$var wire 1 )" and3 $end
$var wire 1 *" and_out $end
$var wire 1 +" or_out $end
$var wire 1 ," s_add $end
$var wire 1 -" s_and $end
$var wire 1 ." s_or $end
$var wire 1 /" s_sub $end
$var wire 1 0" sum $end
$var wire 1 1" xor1 $end
$upscope $end
$scope module bit1 $end
$var wire 1 2" A $end
$var wire 1 3" B $end
$var wire 1 { Binvert $end
$var wire 1 4" Bx $end
$var wire 1 9 Cin $end
$var wire 1 ( Cout $end
$var wire 1 5" Cout_raw $end
$var wire 1 6" R $end
$var wire 2 7" S [1:0] $end
$var wire 1 8" S0_bar $end
$var wire 1 9" S1_bar $end
$var wire 1 :" S_add_sub $end
$var wire 1 ;" and1 $end
$var wire 1 <" and2 $end
$var wire 1 =" and3 $end
$var wire 1 >" and_out $end
$var wire 1 ?" or_out $end
$var wire 1 @" s_add $end
$var wire 1 A" s_and $end
$var wire 1 B" s_or $end
$var wire 1 C" s_sub $end
$var wire 1 D" sum $end
$var wire 1 E" xor1 $end
$upscope $end
$upscope $end
$scope module right $end
$var wire 4 F" in [3:0] $end
$var wire 4 G" out [3:0] $end
$upscope $end
$upscope $end
$scope task print_state $end
$upscope $end
$upscope $end
$enddefinitions $end
$comment Show the parameter values. $end
$dumpall
$end
#0
$dumpvars
b0 G"
b0 F"
1E"
1D"
0C"
0B"
0A"
0@"
1?"
0>"
0="
0<"
0;"
0:"
19"
18"
b0 7"
06"
05"
14"
13"
02"
11"
10"
0/"
0."
0-"
0,"
1+"
0*"
0)"
0("
0'"
0&"
1%"
1$"
b0 #"
0""
0!"
1~
1}
0|
0{
b0 z
b0 y
b11 x
b0 w
1v
1u
0t
0s
0r
0q
1p
0o
0n
0m
0l
0k
1j
1i
b0 h
0g
0f
1e
1d
0c
1b
1a
0`
0_
0^
0]
1\
0[
0Z
0Y
0X
0W
1V
1U
b0 T
0S
0R
1Q
1P
0O
0N
b0 M
b0 L
b11 K
b0 J
b0 I
b0 H
b1000000 G
b0 F
b1000000 E
b0 D
b1110 C
b1111 B
b1000000 A
b0 @
0?
0>
b0 =
b0 <
0;
0:
09
b1000000 8
b1110 7
b1000000 6
b1000000 5
b0 4
b0 3
b1 2
01
00
0/
b0 .
b1111 -
b0 ,
b0 +
b1111 *
b0 )
0(
0'
1&
b1000000 %
b1110 $
b1000000 #
b1000000 "
b0 !
$end
#10000
0&
11
1/
00
b0 #
b0 6
b0 E
b1000 !
b1000 =
b1000 D
0a
b0 M
0g
b1000 <
b10 z
16"
0\
0b
0r
1u
0f
1A"
0D"
15"
0Q
0e
0o
1v
0l
1>"
0E"
1;"
0P
0d
1c
12"
b0 K
b1000110 $
b1000110 7
b1000110 C
b10 J
b10 w
b1000 %
b1000 8
b1000 A
b101 4
b101 I
b101 3
b101 G"
b1100 *
b1100 -
b1100 B
b1010 )
b1010 ,
b1010 @
b1010 H
b1010 F"
#20000
10
b1110 #
b1110 6
b1110 E
b1111 !
b1111 =
b1111 D
1S
b11 M
1g
1^
1R
1r
0u
1f
b1111 <
b11 z
1""
1[
1X
1o
0v
1l
0a
1-"
00"
1!"
1Q
1e
1\
0b
1*"
01"
1'"
1P
1d
1O
1|
b11 K
b1110 $
b1110 7
b1110 C
b11 J
b11 w
b0 2
b1110 %
b1110 8
b1110 A
b1111 4
b1111 I
b1111 3
b1111 G"
b1111 *
b1111 -
b1111 B
b1111 )
b1111 ,
b1111 @
b1111 H
b1111 F"
#30000
1a
0R
1u
0f
10"
0!"
1D"
05"
0^
0r
0-"
0A"
0[
1b
0X
0o
1v
0l
0*"
11"
0'"
0>"
1E"
0;"
0U
1_
0i
1s
0$"
1."
08"
1B"
0O
0c
0|
02"
b0 J
b0 w
b1 2
b1000000 %
b1000000 8
b1000000 A
b0 4
b0 I
b0 3
b0 G"
b1111001 "
b1111001 5
b1111001 G
b1 T
b1 h
b1 #"
b1 7"
b0 )
b0 ,
b0 @
b0 H
b0 F"
b1 F
b1 +
b1 .
b1 L
b1 y
#40000
1u
0f
1D"
05"
0e
04"
0o
1v
0l
0>"
1E"
0;"
0d
03"
1c
12"
b1 K
b1 x
b0 2
b10010 $
b10010 7
b10010 C
b10 J
b10 w
b1000 %
b1000 8
b1000 A
b101 4
b101 I
b101 3
b101 G"
b101 *
b101 -
b101 B
b1010 )
b1010 ,
b1010 @
b1010 H
b1010 F"
#50000
b11000 #
b11000 6
b11000 E
b1001 !
b1001 =
b1001 D
b10 z
0""
0."
00"
b1001 <
b1 M
0g
0+"
01"
0s
0u
0~
0p
0v
0}
0c
b0 x
b1111001 $
b1111001 7
b1111001 C
b0 J
b0 %
b0 8
b0 A
b1 4
b1 I
b100 3
b100 G"
b1 *
b1 -
b1 B
b1000 )
b1000 ,
b1000 @
b1000 H
b1000 F"
#60000
0&
11
0/
10
1g
b100100 #
b100100 6
b100100 E
1q
b10 !
b10 =
b10 D
1u
1:
0a
1R
0D"
1W
0]
b10 M
0S
1k
1&"
1:"
0@"
b10 <
b0 z
06"
1[
0b
1X
0?"
0E"
1U
0V
0_
1i
0j
1$"
0%"
18"
09"
0B"
1O
02"
b1 J
b0 w
b1111001 %
b1111001 8
b1111001 A
b10 4
b10 I
b1000 3
b1000 G"
b100100 "
b100100 5
b100100 G
b10 T
b10 h
b10 #"
b10 7"
b1 )
b1 ,
b1 @
b1 H
b1 F"
b10 F
b10 +
b10 .
b10 L
b10 y
#70000
1/
0&
11
00
b10 z
16"
b0 #
b0 6
b0 E
1@"
b1000 !
b1000 =
b1000 D
1D"
1'
19
1!"
b1000 <
b0 M
0g
1)"
0q
1;
1+"
11"
0u
1f
1~
1p
1v
1m
1}
1c
b1 x
b1 2
b10010 $
b10010 7
b10010 C
b11 J
b110000 %
b110000 8
b110000 A
b110 4
b110 I
b1001 3
b1001 G"
b101 *
b101 -
b101 B
b11 )
b11 ,
b11 @
b11 H
b11 F"
#80000
1&
01
0/
b1000000 #
b1000000 6
b1000000 E
b0 !
b0 =
b0 D
0""
b0 <
b0 z
06"
0'
0,"
0@"
1(
0)"
00"
0D"
15"
0~
0*"
11"
0'"
1("
1?"
1E"
1<"
0}
1|
12"
b0 x
b1111001 $
b1111001 7
b1111001 C
b11 w
b0 2
b1110 %
b1110 8
b1110 A
b1111 4
b1111 I
b1111 3
b1111 G"
b1 *
b1 -
b1 B
b1111 )
b1111 ,
b1111 @
b1111 H
b1111 F"
#90000
0&
0/
11
10
0("
b100100 #
b100100 6
b100100 E
0;
b10 !
b10 =
b10 D
0f
1:
1g
0""
b0 z
06"
1Z
0p
1R
1t
0/"
0C"
1\
0m
0<"
b10 <
b10 M
0S
1u
0U
0i
00"
0D"
0$"
08"
0P
1d
0O
0c
02"
0]
0`
0[
1b
0X
0o
0v
0l
0n
1*"
01"
1'"
0)"
0>"
1E"
0;"
1="
b10 K
b100100 $
b100100 7
b100100 C
b0 J
b1 w
b11001 %
b11001 8
b11001 A
b1000 4
b1000 I
b10 3
b10 G"
0a
0Y
b110000 "
b110000 5
b110000 G
1Q
0e
b11 T
b11 h
1~
14"
b11 #"
b11 7"
b10 *
b10 -
b10 B
b100 )
b100 ,
b100 @
b100 H
b100 F"
1?
1>
b11 F
1N
1{
b11 +
b11 .
b11 L
b11 y
#100000
1/
b110 #
b110 6
b110 E
b1110 !
b1110 =
b1110 D
16"
0(
1C"
05"
0S
b10 M
1g
b1110 <
b11 z
1""
1D"
0="
0'
0`
1t
1;
1/"
09
0Z
1o
1l
1n
0+"
0a
1u
1f
10"
0!"
0Q
1e
0~
0[
1b
0X
1Y
1p
0v
1m
0*"
01"
0'"
1P
0d
1}
1O
1c
0|
b1 K
b1 x
b1 2
b10010 $
b10010 7
b10010 C
b11 J
b0 w
b110000 %
b110000 8
b110000 A
b110 4
b110 I
b1001 3
b1001 G"
b101 *
b101 -
b101 B
b11 )
b11 ,
b11 @
b11 H
b11 F"
#110000
1/
b1111000 #
b1111000 6
b1111000 E
b111 !
b111 =
b111 D
0;
1""
0<"
0="
0f
1/"
09
1S
0n
b11 M
1g
b111 <
b1 z
06"
1'
10"
0!"
1`
0:
1t
0C"
1(
1+"
11"
0)"
1a
0R
1u
0D"
15"
1~
0\
0b
0Y
0o
1v
0l
0m
1>"
0E"
1;"
0}
0O
0c
12"
b0 x
b1111001 $
b1111001 7
b1111001 C
b0 J
b10 w
b0 2
b0 %
b0 8
b0 A
b1 4
b1 I
b100 3
b100 G"
b1 *
b1 -
b1 B
b1000 )
b1000 ,
b1000 @
b1000 H
b1000 F"
#120000
0'
0W
0k
0g
0(
0&"
b0 z
0""
0:"
0?"
b0 <
b0 M
0S
0/
0u
1U
1V
1i
1j
0t
00"
0D"
05"
1$"
1%"
0/"
18"
19"
1O
02"
0P
0`
b100100 #
b100100 6
b100100 E
1\
1b
0p
0v
0+"
01"
0>"
0E"
0;"
b1 J
b0 w
b1111001 %
b1111001 8
b1111001 A
b10 4
b10 I
b1000 3
b1000 G"
b0 K
b1000000 $
b1000000 7
b1000000 C
1a
b10 !
b10 =
b10 D
b11001 "
b11001 5
b11001 G
0Q
0e
b0 T
b0 h
0~
04"
b0 #"
b0 7"
b1 )
b1 ,
b1 @
b1 H
b1 F"
b0 *
b0 -
b0 B
0?
0>
b100 F
0N
0{
b100 +
b100 .
b100 L
b100 y
#130000
0a
1u
1D"
1/
0\
0b
1p
1v
1?"
1E"
b10010 #
b10010 6
b10010 E
0O
1c
12"
b101 !
b101 =
b101 D
b10 J
b10 w
b1000 %
b1000 8
b1000 A
b101 4
b101 I
b101 3
b101 G"
b1010 )
b1010 ,
b1010 @
b1010 H
b1010 F"
#140000
1a
10"
1\
1b
1+"
11"
b1110 #
b1110 6
b1110 E
1O
1|
b1111 !
b1111 =
b1111 D
b11 J
b11 w
b1110 %
b1110 8
b1110 A
b1111 4
b1111 I
b1111 3
b1111 G"
b1111 )
b1111 ,
b1111 @
b1111 H
b1111 F"
#150000
00
0a
0u
00"
b11001 #
b11001 6
b11001 E
0S
b0 M
0g
0""
b1000 <
b10 z
16"
0\
0b
0p
0v
0+"
01"
b100 !
b100 =
b100 D
0U
0_
0i
0s
0$"
0."
08"
1B"
0O
0c
0|
b0 J
b10 w
b0 %
b0 8
b0 A
b1 4
b1 I
b100 3
b100 G"
b10010 "
b10010 5
b10010 G
b1 T
b1 h
b1 #"
b1 7"
b1000 )
b1000 ,
b1000 @
b1000 H
b1000 F"
b101 F
b101 +
b101 .
b101 L
b101 y
#160000
b1010 <
b10 M
1g
10
1s
1u
b10010 #
b10010 6
b10010 E
1p
1v
b101 !
b101 =
b101 D
1c
b10 J
b1000 %
b1000 8
b1000 A
b101 4
b101 I
b101 3
b101 G"
b1010 )
b1010 ,
b1010 @
b1010 H
b1010 F"
#170000
b11 M
1S
b1111 <
b11 z
1""
1_
1a
1."
10"
b1110 #
b1110 6
b1110 E
1\
1b
1+"
11"
b1111 !
b1111 =
b1111 D
1O
1|
b11 J
b11 w
b1110 %
b1110 8
b1110 A
b1111 4
b1111 I
b1111 3
b1111 G"
b1111 )
b1111 ,
b1111 @
b1111 H
b1111 F"
#180000
0&
11
10"
0D"
0/
10
1W
1]
1S
1k
1q
b11 M
1g
1&"
1,"
1""
1:"
0@"
b111 <
b1 z
06"
1~
1+"
11"
0?"
0E"
b1111001 #
b1111001 6
b1111001 E
1U
0V
0_
1i
0j
0s
1$"
0%"
0."
18"
09"
0B"
1}
0|
02"
b1 !
b1 =
b1 D
b1 x
b1 2
b11001 $
b11001 7
b11001 C
b0 w
b110000 %
b110000 8
b110000 A
b110 4
b110 I
b1001 3
b1001 G"
b10 "
b10 5
b10 G
b10 T
b10 h
b10 #"
b10 7"
b100 *
b100 -
b100 B
b11 )
b11 ,
b11 @
b11 H
b11 F"
b110 F
b110 +
b110 .
b110 L
b110 y
#190000
1&
01
1S
b11 M
1g
b1111 <
b11 z
16"
00
1]
1q
1@"
b1000000 #
b1000000 6
b1000000 E
1a
1u
1D"
b0 !
b0 =
b0 D
1Q
1e
1\
1b
1p
1v
1?"
1E"
1P
1d
0O
0c
12"
b11 K
b1111000 $
b1111000 7
b1111000 C
b0 J
b10 w
b0 2
b0 %
b0 8
b0 A
b1 4
b1 I
b100 3
b100 G"
b111 *
b111 -
b111 B
b1000 )
b1000 ,
b1000 @
b1000 H
b1000 F"
#200000
1""
0'
b111 <
b1 z
06"
1,"
09
0@"
10"
0!"
0D"
0~
0*"
11"
0'"
0?"
0E"
0}
1|
02"
b0 x
b110000 $
b110000 7
b110000 C
b1 w
b11001 %
b11001 8
b11001 A
b1000 4
b1000 I
b10 3
b10 G"
b11 *
b11 -
b11 B
b100 )
b100 ,
b100 @
b100 H
b100 F"
