Lab 9/Task 7/T_ff_BH.v
module T_ff_BH (input T, input Reset, input Clk, output reg Q);
    always @ (posedge Clk or posedge Reset)
    begin 
        if (Reset)
            Q <= 0;
        else
            Q <= Q ^ T;
    end
endmodule

Lab 9/Task 7/counter_8bit_t_ff.v
module counter(
    input Clk,
    input Reset,
    input Enable,
    output wire [7:0] Q
);
    wire [7:0] temp;
    assign temp[0] = Enable;
    assign temp[1] = Enable & Q[0];
    assign temp[2] = Enable & Q[0] & Q[1];
    assign temp[3] = Enable & Q[0] & Q[1] & Q[2];
    assign temp[4] = Enable & Q[0] & Q[1] & Q[2] & Q[3];
    assign temp[5] = Enable & Q[0] & Q[1] & Q[2] & Q[3] & Q[4];
    assign temp[6] = Enable & Q[0] & Q[1] & Q[2] & Q[3] & Q[4] & Q[5];
    assign temp[7] = Enable & Q[0] & Q[1] & Q[2] & Q[3] & Q[4] & Q[5] & Q[6];

    T_ff_BH bit0(
        .T(temp[0]),
        .Clk(Clk),
        .Reset(Reset),
        .Q(Q[0])
    );
    T_ff_BH bit1(
        .T(temp[1]),
        .Clk(Clk),
        .Reset(Reset),
        .Q(Q[1])
    );
    T_ff_BH bit2(
        .T(temp[2]),
        .Clk(Clk),
        .Reset(Reset),
        .Q(Q[2])
    );
    T_ff_BH bit3(
        .T(temp[3]),
        .Clk(Clk),
        .Reset(Reset),
        .Q(Q[3])
    );
    T_ff_BH bit4(
        .T(temp[4]),
        .Clk(Clk),
        .Reset(Reset),
        .Q(Q[4])
    );
    T_ff_BH bit5(
        .T(temp[5]),
        .Clk(Clk),
        .Reset(Reset),
        .Q(Q[5])
    );
    T_ff_BH bit6(
        .T(temp[6]),
        .Clk(Clk),
        .Reset(Reset),
        .Q(Q[6])
    );
    T_ff_BH bit7(
        .T(temp[7]),
        .Clk(Clk),
        .Reset(Reset),
        .Q(Q[7])
    );
endmodule

Lab 9/Task 7/counter_8bit_t_ff_tb.v
`timescale 1ns/1ps

module counter_tb;
    reg Clk;
    reg Reset;
    reg Enable;
    wire [7:0] Q;

    counter dut (
        .Clk(Clk),
        .Reset(Reset),
        .Enable(Enable),   
        .Q(Q)
    );

    initial begin
        Clk = 0;
        forever #5 Clk = ~Clk;
    end

    initial begin
        $dumpfile("counter_tb.vcd");
        $dumpvars(0, counter_tb);
        Enable = 0;
        Reset = 1;
        #20;

        Enable = 1; #20;
        Reset = 1; #40;
        Reset = 0; #40;

        Enable = 0; #80;
        Enable = 1; #300;
        $finish;
    end
endmodule

counter_tb.vcd
$date
	Mon Nov 24 21:46:17 2025
$end
$version
	Icarus Verilog
$end
$timescale
	1ps
$end
$scope module counter_tb $end
$var wire 8 ! Q [7:0] $end
$var reg 1 " Clk $end
$var reg 1 # Enable $end
$var reg 1 $ Reset $end
$scope module dut $end
$var wire 1 " Clk $end
$var wire 1 # Enable $end
$var wire 1 $ Reset $end
$var wire 8 % temp [7:0] $end
$var wire 8 & Q [7:0] $end
$scope module bit0 $end
$var wire 1 " Clk $end
$var wire 1 $ Reset $end
$var wire 1 ' T $end
$var reg 1 ( Q $end
$upscope $end
$scope module bit1 $end
$var wire 1 " Clk $end
$var wire 1 $ Reset $end
$var wire 1 ) T $end
$var reg 1 * Q $end
$upscope $end
$scope module bit2 $end
$var wire 1 " Clk $end
$var wire 1 $ Reset $end
$var wire 1 + T $end
$var reg 1 , Q $end
$upscope $end
$scope module bit3 $end
$var wire 1 " Clk $end
$var wire 1 $ Reset $end
$var wire 1 - T $end
$var reg 1 . Q $end
$upscope $end
$scope module bit4 $end
$var wire 1 " Clk $end
$var wire 1 $ Reset $end
$var wire 1 / T $end
$var reg 1 0 Q $end
$upscope $end
$scope module bit5 $end
$var wire 1 " Clk $end
$var wire 1 $ Reset $end
$var wire 1 1 T $end
$var reg 1 2 Q $end
$upscope $end
$scope module bit6 $end
$var wire 1 " Clk $end
$var wire 1 $ Reset $end
$var wire 1 3 T $end
$var reg 1 4 Q $end
$upscope $end
$scope module bit7 $end
$var wire 1 " Clk $end
$var wire 1 $ Reset $end
$var wire 1 5 T $end
$var reg 1 6 Q $end
$upscope $end
$upscope $end
$upscope $end
$enddefinitions $end
$comment Show the parameter values. $end
$dumpall
$end
#0
$dumpvars
06
05
04
03
02
01
00
0/
0.
0-
0,
0+
0*
0)
0(
0'
b0 &
b0 %
1$
0#
0"
b0 !
$end
#5000
1"
#10000
0"
#15000
1"
#20000
1'
0"
b1 %
1#
#25000
1"
#30000
0"
#35000
1"
#40000
0"
#45000
1"
#50000
0"
#55000
1"
#60000
0"
#65000
1"
#70000
0"
#75000
1"
#80000
0"
0$
#85000
1)
b11 %
b1 !
b1 &
1(
1"
#90000
0"
#95000
0)
0+
b1 %
0(
b10 !
b10 &
1*
1"
#100000
0"
#105000
1+
1)
b111 %
b11 !
b11 &
1(
1"
#110000
0"
#115000
0)
0+
0-
b1 %
0(
0*
b100 !
b100 &
1,
1"
#120000
0'
0"
b0 %
0#
#125000
1"
#130000
0"
#135000
1"
#140000
0"
#145000
1"
#150000
0"
#155000
1"
#160000
0"
#165000
1"
#170000
0"
#175000
1"
#180000
0"
#185000
1"
#190000
0"
#195000
1"
#200000
1'
0"
b1 %
1#
#205000
1)
b11 %
b101 !
b101 &
1(
1"
#210000
0"
#215000
0-
0)
0+
b1 %
0(
b110 !
b110 &
1*
1"
#220000
0"
#225000
1-
1+
1)
b1111 %
b111 !
b111 &
1(
1"
#230000
0"
#235000
0)
0+
0-
0/
b1 %
0(
0*
0,
b1000 !
b1000 &
1.
1"
#240000
0"
#245000
1)
b11 %
b1001 !
b1001 &
1(
1"
#250000
0"
#255000
0)
0+
b1 %
0(
b1010 !
b1010 &
1*
1"
#260000
0"
#265000
1+
1)
b111 %
b1011 !
b1011 &
1(
1"
#270000
0"
#275000
0/
0)
0+
0-
b1 %
0(
0*
b1100 !
b1100 &
1,
1"
#280000
0"
#285000
1)
b11 %
b1101 !
b1101 &
1(
1"
#290000
0"
#295000
0/
0-
0)
0+
b1 %
0(
b1110 !
b1110 &
1*
1"
#300000
0"
#305000
1/
1-
1+
1)
b11111 %
b1111 !
b1111 &
1(
1"
#310000
0"
#315000
0)
0+
0-
0/
01
b1 %
0(
0*
0,
0.
b10000 !
b10000 &
10
1"
#320000
0"
#325000
1)
b11 %
b10001 !
b10001 &
1(
1"
#330000
0"
#335000
0)
0+
b1 %
0(
b10010 !
b10010 &
1*
1"
#340000
0"
#345000
1+
1)
b111 %
b10011 !
b10011 &
1(
1"
#350000
0"
#355000
0)
0+
0-
b1 %
0(
0*
b10100 !
b10100 &
1,
1"
#360000
0"
#365000
1)
b11 %
b10101 !
b10101 &
1(
1"
#370000
0"
#375000
0-
0)
0+
b1 %
0(
b10110 !
b10110 &
1*
1"
#380000
0"
#385000
1-
1+
1)
b1111 %
b10111 !
b10111 &
1(
1"
#390000
0"
#395000
01
0)
0+
0-
0/
b1 %
0(
0*
0,
b11000 !
b11000 &
1.
1"
#400000
0"
#405000
1)
b11 %
b11001 !
b11001 &
1(
1"
#410000
0"
#415000
0)
0+
b1 %
0(
b11010 !
b11010 &
1*
1"
#420000
0"
#425000
1+
1)
b111 %
b11011 !
b11011 &
1(
1"
#430000
0"
#435000
01
0/
0)
0+
0-
b1 %
0(
0*
b11100 !
b11100 &
1,
1"
#440000
0"
#445000
1)
b11 %
b11101 !
b11101 &
1(
1"
#450000
0"
#455000
01
0/
0-
0)
0+
b1 %
0(
b11110 !
b11110 &
1*
1"
#460000
0"
#465000
11
1/
1-
1+
1)
b111111 %
b11111 !
b11111 &
1(
1"
#470000
0"
#475000
0)
0+
0-
0/
01
03
b1 %
0(
0*
0,
0.
00
b100000 !
b100000 &
12
1"
#480000
0"
#485000
1)
b11 %
b100001 !
b100001 &
1(
1"
#490000
0"
#495000
0)
0+
b1 %
0(
b100010 !
b100010 &
1*
1"
