Lab 9/Task 8/down_counter.v
module down_counter(
    input Clk,
    input load,
    input enable,
    input clear,
    output reg [3:0] Q
);
    wire cnt_done;

    assign cnt_done = ~| Q;

    always @(posedge Clk) begin
        if (clear)
            Q <= 0;
        else if (enable)
            if (load | cnt_done)
                Q <= 4'b1010; // decimal 10
            else
                Q <= Q - 1;
    end
endmodule

Lab 9/Task 8/down_counter_tb.v
`timescale 1ns/1ps

module down_counter_tb;
    reg Clk;
    reg load;
    reg enable;
    reg clear;
    wire [3:0] Q;

    down_counter dut (
        .Clk(Clk),
        .load(load),
        .enable(enable),
        .clear(clear),
        .Q(Q)
    );

    initial begin
        Clk = 0;
        forever #5 Clk = ~Clk;
    end

    initial begin
        $dumpfile("down_counter_tb.vcd");
        $dumpvars(0, down_counter_tb);
        
        // Initial conditions
        load = 0;
        enable = 0;
        clear = 0;
        #20;

        enable = 1; #20;
        clear = 1; #10;
        clear = 0; #20;

        load = 1; #10;
        load = 0; #80;

        enable = 0; #40;
        enable = 1; #190;

        $finish;
    end
endmodule

down_counter_tb.vcd
$date
	Mon Nov 24 22:06:26 2025
$end
$version
	Icarus Verilog
$end
$timescale
	1ps
$end
$scope module down_counter_tb $end
$var wire 4 ! Q [3:0] $end
$var reg 1 " Clk $end
$var reg 1 # clear $end
$var reg 1 $ enable $end
$var reg 1 % load $end
$scope module dut $end
$var wire 1 " Clk $end
$var wire 1 # clear $end
$var wire 1 $ enable $end
$var wire 1 % load $end
$var wire 1 & cnt_done $end
$var reg 4 ' Q [3:0] $end
$upscope $end
$upscope $end
$enddefinitions $end
$comment Show the parameter values. $end
$dumpall
$end
#0
$dumpvars
bx '
x&
0%
0$
0#
0"
bx !
$end
#5000
1"
#10000
0"
#15000
1"
#20000
0"
1$
#25000
1"
#30000
0"
#35000
1"
#40000
0"
1#
#45000
1&
b0 !
b0 '
1"
#50000
0"
0#
#55000
0&
b1010 !
b1010 '
1"
#60000
0"
#65000
b1001 !
b1001 '
1"
#70000
0"
1%
#75000
b1010 !
b1010 '
1"
#80000
0"
0%
#85000
b1001 !
b1001 '
1"
#90000
0"
#95000
b1000 !
b1000 '
1"
#100000
0"
#105000
b111 !
b111 '
1"
#110000
0"
#115000
b110 !
b110 '
1"
#120000
0"
#125000
b101 !
b101 '
1"
#130000
0"
#135000
b100 !
b100 '
1"
#140000
0"
#145000
b11 !
b11 '
1"
#150000
0"
#155000
b10 !
b10 '
1"
#160000
0"
0$
#165000
1"
#170000
0"
#175000
1"
#180000
0"
#185000
1"
#190000
0"
#195000
1"
#200000
0"
1$
#205000
b1 !
b1 '
1"
#210000
0"
#215000
1&
b0 !
b0 '
1"
#220000
0"
#225000
0&
b1010 !
b1010 '
1"
#230000
0"
#235000
b1001 !
b1001 '
1"
#240000
0"
#245000
b1000 !
b1000 '
1"
#250000
0"
#255000
b111 !
b111 '
1"
#260000
0"
#265000
b110 !
b110 '
1"
#270000
0"
#275000
b101 !
b101 '
1"
#280000
0"
#285000
b100 !
b100 '
1"
#290000
0"
#295000
b11 !
b11 '
1"
#300000
0"
#305000
b10 !
b10 '
1"
#310000
0"
#315000
b1 !
b1 '
1"
#320000
0"
#325000
1&
b0 !
b0 '
1"
#330000
0"
#335000
0&
b1010 !
b1010 '
1"
#340000
0"
#345000
b1001 !
b1001 '
1"
#350000
0"
#355000
b1000 !
b1000 '
1"
#360000
0"
#365000
b111 !
b111 '
1"
#370000
0"
#375000
b110 !
b110 '
1"
#380000
0"
#385000
b101 !
b101 '
1"
