t_flip_flop.v
module T_flip_flop (
    input T,
    input Clk,
    input Reset,
    output reg Q
);
    always @(posedge Clk or posedge Reset) begin
        if (Reset)
            Q <= 0;
        else if (T)
            Q <= ~Q;
    end
endmodule

counter_2bit.v
module counter(
    input Clk,
    input Reset,
    input Enable,
    output wire [1:0] Q
);
    wire [1:0] temp;
    assign temp[0] = Enable;
    assign temp[1] = Enable & Q[0];

    T_flip_flop bit0(
        .T(temp[0]),
        .Clk(Clk),
        .Reset(Reset),
        .Q(Q[0])
    );
    T_flip_flop bit1(
        .T(temp[1]),
        .Clk(Clk),
        .Reset(Reset),
        .Q(Q[1])
    );
endmodule

Lab 10/clk_div.v
module clk_div(
    input clk,
    input reset,
    output clk_en
);
    reg [3:0] clk_count;
    always @(posedge clk)
    begin
        if(reset)
            clk_count <= 0;
        else
            clk_count <=clk_count + 1;
    end
    assign clk_en = &clk_count;
endmodule

Lab 10/thunderbird.v
module thunderbird_wrapper (
    input Clk,
    input Reset,
    input Right_switch,
    input Left_switch,

    output L_A,
    output L_B,
    output L_C,
    output R_A,
    output R_B,
    output R_C
);
    wire Reset_Left = (~Left_switch | Reset);
    wire Reset_Right = (~Right_switch | Reset);

    wire [1:0] Q_Left;
    wire [1:0] Q_Right;
    wire Clk_div;

    
    clk_div div(
        .clk(Clk),
        .reset(Reset),
        .clk_en(Clk_div)
    );

    counter left (
        .Clk(Clk),
        .Reset(Reset_Left),
        .Enable(Left_switch & Clk_div),
        .Q(Q_Left)
    );

    counter right (
        .Clk(Clk),
        .Reset(Reset_Right),
        .Enable(Right_switch & Clk_div),
        .Q(Q_Right)
    );

    assign L_A = (Q_Left[1] | Q_Left[0]);    
    assign L_B = Q_Left[1]; 
    assign L_C = (Q_Left[1] & Q_Left[0]);

    assign R_A = (Q_Right[1] | Q_Right[0]);
    assign R_B = Q_Right[1];
    assign R_C = (Q_Right[1] & Q_Right[0]);
endmodule

Lab 10/thunderbird_tb.v
`timescale 1ns/1ps

module thunderbird_tb;
    reg Clk;
    reg Reset;
    reg Right_switch;
    reg Left_switch;

    wire L_A;
    wire L_B;
    wire L_C;

    wire R_A;
    wire R_B;
    wire R_C;

    wire Clk_div;

    thunderbird_wrapper dut(
        .Clk(Clk),
        .Reset(Reset),
        .Right_switch(Right_switch),
        .Left_switch(Left_switch),

        .L_A(L_A),
        .L_B(L_B),
        .L_C(L_C),
        .R_A(R_A),
        .R_B(R_B),
        .R_C(R_C)
    );

    initial begin
        Clk = 0;
        forever #1 Clk = ~Clk;
    end

    initial begin
        $dumpfile("thunderbird_tb.vcd");
        $dumpvars(0, thunderbird_tb);

        Reset = 1;
        Left_switch = 0;
        Right_switch = 0;
        #2;
        Reset = 0;

        Left_switch = 1;
        Right_switch = 1; #1000;
        Left_switch = 0;
        Right_switch = 0; #500;

        Left_switch = 1;
        Right_switch = 1; #25;
        Left_switch = 0;
        Right_switch = 0; #25;

        $finish;

    end
endmodule

thunderbird_tb.vcd
$date
	Wed Nov 26 13:47:59 2025
$end
$version
	Icarus Verilog
$end
$timescale
	1ps
$end
$scope module thunderbird_tb $end
$var wire 1 ! R_C $end
$var wire 1 " R_B $end
$var wire 1 # R_A $end
$var wire 1 $ L_C $end
$var wire 1 % L_B $end
$var wire 1 & L_A $end
$var reg 1 ' Clk $end
$var reg 1 ( Left_switch $end
$var reg 1 ) Reset $end
$var reg 1 * Right_switch $end
$scope module dut $end
$var wire 1 ' Clk $end
$var wire 1 & L_A $end
$var wire 1 $ L_C $end
$var wire 1 ( Left_switch $end
$var wire 1 # R_A $end
$var wire 1 ! R_C $end
$var wire 1 ) Reset $end
$var wire 1 + Reset_Left $end
$var wire 1 , Reset_Right $end
$var wire 1 * Right_switch $end
$var wire 1 " R_B $end
$var wire 2 - Q_Right [1:0] $end
$var wire 2 . Q_Left [1:0] $end
$var wire 1 % L_B $end
$var wire 1 / Clk_div $end
$scope module div $end
$var wire 1 ' clk $end
$var wire 1 ) reset $end
$var wire 1 / clk_en $end
$var reg 4 0 clk_count [3:0] $end
$upscope $end
$scope module left $end
$var wire 1 ' Clk $end
$var wire 1 1 Enable $end
$var wire 1 + Reset $end
$var wire 2 2 temp [1:0] $end
$var wire 2 3 Q [1:0] $end
$scope module bit0 $end
$var wire 1 ' Clk $end
$var wire 1 + Reset $end
$var wire 1 4 T $end
$var reg 1 5 Q $end
$upscope $end
$scope module bit1 $end
$var wire 1 ' Clk $end
$var wire 1 + Reset $end
$var wire 1 6 T $end
$var reg 1 7 Q $end
$upscope $end
$upscope $end
$scope module right $end
$var wire 1 ' Clk $end
$var wire 1 8 Enable $end
$var wire 1 , Reset $end
$var wire 2 9 temp [1:0] $end
$var wire 2 : Q [1:0] $end
$scope module bit0 $end
$var wire 1 ' Clk $end
$var wire 1 , Reset $end
$var wire 1 ; T $end
$var reg 1 < Q $end
$upscope $end
$scope module bit1 $end
$var wire 1 ' Clk $end
$var wire 1 , Reset $end
$var wire 1 = T $end
$var reg 1 > Q $end
$upscope $end
$upscope $end
$upscope $end
$upscope $end
$enddefinitions $end
$comment Show the parameter values. $end
$dumpall
$end
#0
$dumpvars
0>
0=
0<
0;
b0 :
b0 9
08
07
06
05
04
b0 3
b0 2
01
bx 0
x/
b0 .
b0 -
1,
1+
0*
1)
0(
0'
0&
0%
0$
0#
0"
0!
$end
#1000
0/
b0 0
1'
#2000
0,
0+
0'
1*
1(
0)
#3000
b1 0
1'
#4000
0'
#5000
b10 0
1'
#6000
0'
#7000
b11 0
1'
#8000
0'
#9000
b100 0
1'
#10000
0'
#11000
b101 0
1'
#12000
0'
#13000
b110 0
1'
#14000
0'
#15000
b111 0
1'
#16000
0'
#17000
b1000 0
1'
#18000
0'
#19000
b1001 0
1'
#20000
0'
#21000
b1010 0
1'
#22000
0'
#23000
b1011 0
1'
#24000
0'
#25000
b1100 0
1'
#26000
0'
#27000
b1101 0
1'
#28000
0'
#29000
b1110 0
1'
#30000
0'
#31000
1;
14
b1 9
18
b1 2
11
1/
b1111 0
1'
#32000
0'
#33000
0;
04
1&
1#
b0 9
08
b0 2
01
0/
b0 0
b1 .
b1 3
15
b1 -
b1 :
1<
1'
#34000
0'
#35000
b1 0
1'
#36000
0'
#37000
b10 0
1'
#38000
0'
#39000
b11 0
1'
#40000
0'
#41000
b100 0
1'
#42000
0'
#43000
b101 0
1'
#44000
0'
#45000
b110 0
1'
#46000
0'
#47000
b111 0
1'
#48000
0'
#49000
b1000 0
1'
#50000
0'
#51000
b1001 0
1'
#52000
0'
#53000
b1010 0
1'
#54000
0'
#55000
b1011 0
1'
#56000
0'
#57000
b1100 0
1'
#58000
0'
#59000
b1101 0
1'
#60000
0'
#61000
b1110 0
1'
#62000
0'
#63000
1=
16
1;
14
b11 9
18
b11 2
11
1/
b1111 0
1'
#64000
0'
#65000
06
0=
0;
04
b0 9
08
b0 2
01
1%
1"
0/
b0 0
17
b10 .
b10 3
05
1>
b10 -
b10 :
0<
1'
#66000
0'
#67000
b1 0
1'
#68000
0'
#69000
b10 0
1'
#70000
0'
#71000
b11 0
1'
#72000
0'
#73000
b100 0
1'
#74000
0'
#75000
b101 0
1'
#76000
0'
#77000
b110 0
1'
#78000
0'
#79000
b111 0
1'
#80000
0'
#81000
b1000 0
1'
#82000
0'
#83000
b1001 0
1'
#84000
0'
#85000
b1010 0
1'
#86000
0'
#87000
b1011 0
1'
#88000
0'
#89000
b1100 0
1'
#90000
0'
#91000
b1101 0
1'
#92000
0'
#93000
b1110 0
1'
#94000
0'
#95000
1;
14
b1 9
18
b1 2
11
1/
b1111 0
1'
#96000
0'
#97000
0;
04
1$
1!
b0 9
08
b0 2
01
0/
b0 0
b11 .
b11 3
15
b11 -
b11 :
1<
1'
#98000
0'
#99000
b1 0
1'
#100000
0'
#101000
b10 0
1'
#102000
0'
#103000
b11 0
1'
#104000
0'
#105000
b100 0
1'
#106000
0'
#107000
b101 0
1'
#108000
0'
#109000
b110 0
1'
#110000
0'
#111000
b111 0
1'
#112000
0'
#113000
b1000 0
1'
#114000
0'
#115000
b1001 0
1'
#116000
0'
#117000
b1010 0
1'
#118000
0'
#119000
b1011 0
1'
#120000
0'
#121000
b1100 0
1'
#122000
0'
#123000
b1101 0
1'
#124000
0'
#125000
b1110 0
1'
#126000
0'
#127000
1=
16
1;
14
b11 9
18
b11 2
11
1/
b1111 0
1'
#128000
0'
#129000
06
0=
0;
04
0$
0&
0!
0#
b0 9
08
b0 2
01
0%
0"
0/
b0 0
07
b0 .
b0 3
05
0>
b0 -
b0 :
0<
1'
#130000
0'
#131000
b1 0
1'
#132000
0'
#133000
b10 0
1'
#134000
0'
#135000
b11 0
1'
#136000
0'
#137000
b100 0
1'
#138000
0'
#139000
b101 0
1'
#140000
0'
#141000
b110 0
1'
#142000
0'
#143000
b111 0
1'
#144000
0'
#145000
b1000 0
1'
#146000
0'
#147000
b1001 0
1'
#148000
0'
#149000
b1010 0
1'
#150000
0'
#151000
b1011 0
1'
#152000
0'
#153000
b1100 0
1'
#154000
0'
#155000
b1101 0
1'
#156000
0'
#157000
b1110 0
1'
#158000
0'
#159000
1;
14
b1 9
18
b1 2
11
1/
b1111 0
1'
#160000
0'
#161000
0;
04
1&
1#
b0 9
08
b0 2
01
0/
b0 0
b1 .
b1 3
15
b1 -
b1 :
1<
1'
#162000
0'
#163000
b1 0
1'
#164000
0'
#165000
b10 0
1'
#166000
0'
#167000
b11 0
1'
#168000
0'
#169000
b100 0
1'
#170000
0'
#171000
b101 0
1'
#172000
0'
#173000
b110 0
1'
#174000
0'
#175000
b111 0
1'
#176000
0'
#177000
b1000 0
1'
#178000
0'
#179000
b1001 0
1'
#180000
0'
#181000
b1010 0
1'
#182000
0'
#183000
b1011 0
1'
#184000
0'
#185000
b1100 0
1'
#186000
0'
#187000
b1101 0
1'
#188000
0'
#189000
b1110 0
1'
#190000
0'
#191000
1=
16
1;
14
b11 9
18
b11 2
11
1/
b1111 0
1'
#192000
0'
#193000
06
0=
0;
04
b0 9
08
b0 2
01
1%
1"
0/
b0 0
17
b10 .
b10 3
05
1>
b10 -
b10 :
0<
1'
#194000
0'
#195000
b1 0
1'
#196000
0'
#197000
b10 0
1'
#198000
0'
#199000
b11 0
1'
#200000
0'
#201000
b100 0
1'
#202000
0'
#203000
b101 0
1'
#204000
0'
#205000
b110 0
1'
#206000
0'
#207000
b111 0
1'
#208000
0'
#209000
b1000 0
1'
#210000
0'
#211000
b1001 0
1'
#212000
0'
#213000
b1010 0
1'
#214000
0'
#215000
b1011 0
1'
#216000
0'
#217000
b1100 0
1'
#218000
0'
#219000
b1101 0
1'
#220000
0'
#221000
b1110 0
1'
#222000
0'
#223000
1;
14
b1 9
18
b1 2
11
1/
b1111 0
1'
#224000
0'
#225000
0;
04
1$
1!
b0 9
08
b0 2
01
0/
b0 0
b11 .
b11 3
15
b11 -
b11 :
1<
1'
#226000
0'
#227000
b1 0
1'
#228000
0'
#229000
b10 0
1'
#230000
0'
#231000
b11 0
1'
#232000
0'
#233000
b100 0
1'
#234000
0'
#235000
b101 0
1'
#236000
0'
#237000
b110 0
1'
#238000
0'
#239000
b111 0
1'
#240000
0'
#241000
b1000 0
1'
#242000
0'
#243000
b1001 0
1'
#244000
0'
#245000
b1010 0
1'
#246000
0'
#247000
b1011 0
1'
#248000
0'
#249000
b1100 0
1'
#250000
0'
#251000
b1101 0
1'
#252000
0'
#253000
b1110 0
1'
#254000
0'
#255000
1=
16
1;
14
b11 9
18
b11 2
11
1/
b1111 0
1'
#256000
0'
#257000
06
0=
0;
04
0$
0&
0!
0#
b0 9
08
b0 2
01
0%
0"
0/
b0 0
07
b0 .
b0 3
05
0>
b0 -
b0 :
0<
1'
#258000
0'
#259000
b1 0
1'
#260000
0'
#261000
b10 0
1'
#262000
0'
#263000
b11 0
1'
#264000
0'
#265000
b100 0
1'
#266000
0'
#267000
b101 0
1'
#268000
0'
#269000
b110 0
1'
#270000
0'
#271000
b111 0
1'
#272000
0'
#273000
b1000 0
1'
#274000
0'
#275000
b1001 0
1'
#276000
0'
#277000
b1010 0
1'
#278000
0'
#279000
b1011 0
1'
#280000
0'
#281000
b1100 0
1'
#282000
0'
#283000
b1101 0
1'
#284000
0'
#285000
b1110 0
1'
#286000
0'
#287000
1;
14
b1 9
18
b1 2
11
1/
b1111 0
1'
#288000
0'
#289000
0;
04
1&
1#
b0 9
08
b0 2
01
0/
b0 0
b1 .
b1 3
15
b1 -
b1 :
1<
1'
#290000
0'
#291000
b1 0
1'
#292000
0'
#293000
b10 0
1'
#294000
0'
#295000
b11 0
1'
#296000
0'
#297000
b100 0
1'
#298000
0'
#299000
b101 0
1'
#300000
0'
#301000
b110 0
1'
#302000
0'
#303000
b111 0
1'
#304000
0'
#305000
b1000 0
1'
#306000
0'
#307000
b1001 0
1'
#308000
0'
#309000
b1010 0
1'
#310000
0'
#311000
b1011 0
1'
#312000
0'
#313000
b1100 0
1'
#314000
0'
#315000
b1101 0
1'
#316000
0'
#317000
b1110 0
1'
#318000
0'
#319000
1=
16
1;
14
b11 9
18
b11 2
11
1/
b1111 0
1'
#320000
0'
#321000
06
0=
0;
04
b0 9
08
b0 2
01
1%
1"
0/
b0 0
17
b10 .
b10 3
05
1>
b10 -
b10 :
0<
1'
#322000
0'
#323000
b1 0
1'
#324000
0'
#325000
b10 0
1'
#326000
0'
#327000
b11 0
1'
#328000
0'
#329000
b100 0
1'
#330000
0'
#331000
b101 0
1'
#332000
0'
#333000
b110 0
1'
#334000
0'
#335000
b111 0
1'
#336000
0'
#337000
b1000 0
1'
#338000
0'
#339000
b1001 0
1'
#340000
0'
#341000
b1010 0
1'
#342000
0'
#343000
b1011 0
1'
#344000
0'
#345000
b1100 0
1'
#346000
0'
#347000
b1101 0
1'
#348000
0'
#349000
b1110 0
1'
#350000
0'
#351000
1;
14
b1 9
18
b1 2
11
1/
b1111 0
1'
#352000
0'
#353000
0;
04
1$
1!
b0 9
08
b0 2
01
0/
b0 0
b11 .
b11 3
15
b11 -
b11 :
1<
1'
#354000
0'
#355000
b1 0
1'
#356000
0'
#357000
b10 0
1'
#358000
0'
#359000
b11 0
1'
#360000
0'
#361000
b100 0
1'
#362000
0'
#363000
b101 0
1'
#364000
0'
#365000
b110 0
1'
#366000
0'
#367000
b111 0
1'
#368000
0'
#369000
b1000 0
1'
#370000
0'
#371000
b1001 0
1'
#372000
0'
#373000
b1010 0
1'
#374000
0'
#375000
b1011 0
1'
#376000
0'
#377000
b1100 0
1'
#378000
0'
#379000
b1101 0
1'
#380000
0'
#381000
b1110 0
1'
#382000
0'
#383000
1=
16
1;
14
b11 9
18
b11 2
11
1/
b1111 0
1'
#384000
0'
#385000
06
0=
0;
04
0$
0&
0!
0#
b0 9
08
b0 2
01
0%
0"
0/
b0 0
07
b0 .
b0 3
05
0>
b0 -
b0 :
0<
1'
#386000
0'
#387000
b1 0
1'
#388000
0'
#389000
b10 0
1'
#390000
0'
#391000
b11 0
1'
#392000
0'
#393000
b100 0
1'
#394000
0'
#395000
b101 0
1'
#396000
0'
#397000
b110 0
1'
#398000
0'
#399000
b111 0
1'
#400000
0'
#401000
b1000 0
1'
#402000
0'
#403000
b1001 0
1'
#404000
0'
#405000
b1010 0
1'
#406000
0'
#407000
b1011 0
1'
#408000
0'
#409000
b1100 0
1'
#410000
0'
#411000
b1101 0
1'
#412000
0'
#413000
b1110 0
1'
#414000
0'
#415000
1;
14
b1 9
18
b1 2
11
1/
b1111 0
1'
#416000
0'
#417000
0;
04
1&
1#
b0 9
08
b0 2
01
0/
b0 0
b1 .
b1 3
15
b1 -
b1 :
1<
1'
#418000
0'
#419000
b1 0
1'
#420000
0'
#421000
b10 0
1'
#422000
0'
#423000
b11 0
1'
#424000
0'
#425000
b100 0
1'
#426000
0'
#427000
b101 0
1'
#428000
0'
#429000
b110 0
1'
#430000
0'
#431000
b111 0
1'
#432000
0'
#433000
b1000 0
1'
#434000
0'
#435000
b1001 0
1'
#436000
0'
#437000
b1010 0
1'
#438000
0'
#439000
b1011 0
1'
#440000
0'
#441000
b1100 0
1'
#442000
0'
#443000
b1101 0
1'
#444000
0'
#445000
b1110 0
1'
#446000
0'
#447000
1=
16
1;
14
b11 9
18
b11 2
11
1/
b1111 0
1'
#448000
0'
#449000
06
0=
0;
04
b0 9
08
b0 2
01
1%
1"
0/
b0 0
17
b10 .
b10 3
05
1>
b10 -
b10 :
0<
1'
#450000
0'
#451000
b1 0
1'
#452000
0'
#453000
b10 0
1'
#454000
0'
#455000
b11 0
1'
#456000
0'
#457000
b100 0
1'
#458000
0'
#459000
b101 0
1'
#460000
0'
#461000
b110 0
1'
#462000
0'
#463000
b111 0
1'
#464000
0'
#465000
b1000 0
1'
#466000
0'
#467000
b1001 0
1'
#468000
0'
#469000
b1010 0
1'
#470000
0'
#471000
b1011 0
1'
#472000
0'
#473000
b1100 0
1'
#474000
0'
#475000
b1101 0
1'
#476000
0'
#477000
b1110 0
1'
#478000
0'
#479000
1;
14
b1 9
18
b1 2
11
1/
b1111 0
1'
#480000
0'
#481000
0;
04
1$
1!
b0 9
08
b0 2
01
0/
b0 0
b11 .
b11 3
15
b11 -
b11 :
1<
1'
#482000
0'
#483000
b1 0
1'
#484000
0'
#485000
b10 0
1'
#486000
0'
#487000
b11 0
1'
#488000
0'
#489000
b100 0
1'
#490000
0'
#491000
b101 0
1'
#492000
0'
#493000
b110 0
1'
#494000
0'
#495000
b111 0
1'
#496000
0'
#497000
b1000 0
1'
#498000
0'
#499000
b1001 0
1'
#500000
0'
#501000
b1010 0
1'
#502000
0'
#503000
b1011 0
1'
#504000
0'
#505000
b1100 0
1'
#506000
0'
#507000
b1101 0
1'
#508000
0'
#509000
b1110 0
1'
#510000
0'
#511000
1=
16
1;
14
b11 9
18
b11 2
11
1/
b1111 0
1'
#512000
0'
#513000
06
0=
0;
04
0$
0&
0!
0#
b0 9
08
b0 2
01
0%
0"
0/
b0 0
07
b0 .
b0 3
05
0>
b0 -
b0 :
0<
1'
#514000
0'
#515000
b1 0
1'
#516000
0'
#517000
b10 0
1'
#518000
0'
#519000
b11 0
1'
#520000
0'
#521000
b100 0
1'
#522000
0'
#523000
b101 0
1'
#524000
0'
#525000
b110 0
1'
#526000
0'
#527000
b111 0
1'
#528000
0'
#529000
b1000 0
1'
#530000
0'
#531000
b1001 0
1'
#532000
0'
#533000
b1010 0
1'
#534000
0'
#535000
b1011 0
1'
#536000
0'
#537000
b1100 0
1'
#538000
0'
#539000
b1101 0
1'
#540000
0'
#541000
b1110 0
1'
#542000
0'
#543000
1;
14
b1 9
18
b1 2
11
1/
b1111 0
1'
#544000
0'
#545000
0;
04
1&
1#
b0 9
08
b0 2
01
0/
b0 0
b1 .
b1 3
15
b1 -
b1 :
1<
1'
#546000
0'
#547000
b1 0
1'
#548000
0'
#549000
b10 0
1'
#550000
0'
#551000
b11 0
1'
#552000
0'
#553000
b100 0
1'
#554000
0'
#555000
b101 0
1'
#556000
0'
#557000
b110 0
1'
#558000
0'
#559000
b111 0
1'
#560000
0'
#561000
b1000 0
1'
#562000
0'
#563000
b1001 0
1'
#564000
0'
#565000
b1010 0
1'
#566000
0'
#567000
b1011 0
1'
#568000
0'
#569000
b1100 0
1'
#570000
0'
#571000
b1101 0
1'
#572000
0'
#573000
b1110 0
1'
#574000
0'
#575000
1=
16
1;
14
b11 9
18
b11 2
11
1/
b1111 0
1'
#576000
0'
#577000
06
0=
0;
04
b0 9
08
b0 2
01
1%
1"
0/
b0 0
17
b10 .
b10 3
05
1>
b10 -
b10 :
0<
1'
#578000
0'
#579000
b1 0
1'
#580000
0'
#581000
b10 0
1'
#582000
0'
#583000
b11 0
1'
#584000
0'
#585000
b100 0
1'
#586000
0'
#587000
b101 0
1'
#588000
0'
#589000
b110 0
1'
#590000
0'
#591000
b111 0
1'
#592000
0'
#593000
b1000 0
1'
#594000
0'
#595000
b1001 0
1'
#596000
0'
#597000
b1010 0
1'
#598000
0'
#599000
b1011 0
1'
#600000
0'
#601000
b1100 0
1'
#602000
0'
#603000
b1101 0
1'
#604000
0'
#605000
b1110 0
1'
#606000
0'
#607000
1;
14
b1 9
18
b1 2
11
1/
b1111 0
1'
#608000
0'
#609000
0;
04
1$
1!
b0 9
08
b0 2
01
0/
b0 0
b11 .
b11 3
15
b11 -
b11 :
1<
1'
#610000
0'
#611000
b1 0
1'
#612000
0'
#613000
b10 0
1'
#614000
0'
#615000
b11 0
1'
#616000
0'
#617000
b100 0
1'
#618000
0'
#619000
b101 0
1'
#620000
0'
#621000
b110 0
1'
#622000
0'
#623000
b111 0
1'
#624000
0'
#625000
b1000 0
1'
#626000
0'
#627000
b1001 0
1'
#628000
0'
#629000
b1010 0
1'
#630000
0'
#631000
b1011 0
1'
#632000
0'
#633000
b1100 0
1'
#634000
0'
#635000
b1101 0
1'
#636000
0'
#637000
b1110 0
1'
#638000
0'
#639000
1=
16
1;
14
b11 9
18
b11 2
11
1/
b1111 0
1'
#640000
0'
#641000
06
0=
0;
04
0$
0&
0!
0#
b0 9
08
b0 2
01
0%
0"
0/
b0 0
07
b0 .
b0 3
05
0>
b0 -
b0 :
0<
1'
#642000
0'
#643000
b1 0
1'
#644000
0'
#645000
b10 0
1'
#646000
0'
#647000
b11 0
1'
#648000
0'
#649000
b100 0
1'
#650000
0'
#651000
b101 0
1'
#652000
0'
#653000
b110 0
1'
#654000
0'
#655000
b111 0
1'
#656000
0'
#657000
b1000 0
1'
#658000
0'
#659000
b1001 0
1'
#660000
0'
#661000
b1010 0
1'
#662000
0'
#663000
b1011 0
1'
#664000
0'
#665000
b1100 0
1'
#666000
0'
#667000
b1101 0
1'
#668000
0'
#669000
b1110 0
1'
#670000
0'
#671000
1;
14
b1 9
18
b1 2
11
1/
b1111 0
1'
#672000
0'
#673000
0;
04
1&
1#
b0 9
08
b0 2
01
0/
b0 0
b1 .
b1 3
15
b1 -
b1 :
1<
1'
#674000
0'
#675000
b1 0
1'
#676000
0'
#677000
b10 0
1'
#678000
0'
#679000
b11 0
1'
#680000
0'
#681000
b100 0
1'
#682000
0'
#683000
b101 0
1'
#684000
0'
#685000
b110 0
1'
#686000
0'
#687000
b111 0
1'
#688000
0'
#689000
b1000 0
1'
#690000
0'
#691000
b1001 0
1'
#692000
0'
#693000
b1010 0
1'
#694000
0'
#695000
b1011 0
1'
#696000
0'
#697000
b1100 0
1'
#698000
0'
#699000
b1101 0
1'
#700000
0'
#701000
b1110 0
1'
#702000
0'
#703000
1=
16
1;
14
b11 9
18
b11 2
11
1/
b1111 0
1'
#704000
0'
#705000
06
0=
0;
04
b0 9
08
b0 2
01
1%
1"
0/
b0 0
17
b10 .
b10 3
05
1>
b10 -
b10 :
0<
1'
#706000
0'
#707000
b1 0
1'
#708000
0'
#709000
b10 0
1'
#710000
0'
#711000
b11 0
1'
#712000
0'
#713000
b100 0
1'
#714000
0'
#715000
b101 0
1'
#716000
0'
#717000
b110 0
1'
#718000
0'
#719000
b111 0
1'
#720000
0'
#721000
b1000 0
1'
#722000
0'
#723000
b1001 0
1'
#724000
0'
#725000
b1010 0
1'
#726000
0'
#727000
b1011 0
1'
#728000
0'
#729000
b1100 0
1'
#730000
0'
#731000
b1101 0
1'
#732000
0'
#733000
b1110 0
1'
#734000
0'
#735000
1;
14
b1 9
18
b1 2
11
1/
b1111 0
1'
#736000
0'
#737000
0;
04
1$
1!
b0 9
08
b0 2
01
0/
b0 0
b11 .
b11 3
15
b11 -
b11 :
1<
1'
#738000
0'
#739000
b1 0
1'
#740000
0'
#741000
b10 0
1'
#742000
0'
#743000
b11 0
1'
#744000
0'
#745000
b100 0
1'
#746000
0'
#747000
b101 0
1'
#748000
0'
#749000
b110 0
1'
#750000
0'
#751000
b111 0
1'
#752000
0'
#753000
b1000 0
1'
#754000
0'
#755000
b1001 0
1'
#756000
0'
#757000
b1010 0
1'
#758000
0'
#759000
b1011 0
1'
#760000
0'
#761000
b1100 0
1'
#762000
0'
#763000
b1101 0
1'
#764000
0'
#765000
b1110 0
1'
#766000
0'
#767000
1=
16
1;
14
b11 9
18
b11 2
11
1/
b1111 0
1'
#768000
0'
#769000
06
0=
0;
04
0$
0&
0!
0#
b0 9
08
b0 2
01
0%
0"
0/
b0 0
07
b0 .
b0 3
05
0>
b0 -
b0 :
0<
1'
#770000
0'
#771000
b1 0
1'
#772000
0'
#773000
b10 0
1'
#774000
0'
#775000
b11 0
1'
#776000
0'
#777000
b100 0
1'
#778000
0'
#779000
b101 0
1'
#780000
0'
#781000
b110 0
1'
#782000
0'
#783000
b111 0
1'
#784000
0'
#785000
b1000 0
1'
#786000
0'
#787000
b1001 0
1'
#788000
0'
#789000
b1010 0
1'
#790000
0'
#791000
b1011 0
1'
#792000
0'
#793000
b1100 0
1'
#794000
0'
#795000
b1101 0
1'
#796000
0'
#797000
b1110 0
1'
#798000
0'
#799000
1;
14
b1 9
18
b1 2
11
1/
b1111 0
1'
#800000
0'
#801000
0;
04
1&
1#
b0 9
08
b0 2
01
0/
b0 0
b1 .
b1 3
15
b1 -
b1 :
1<
1'
#802000
0'
#803000
b1 0
1'
#804000
0'
#805000
b10 0
1'
#806000
0'
#807000
b11 0
1'
#808000
0'
#809000
b100 0
1'
#810000
0'
#811000
b101 0
1'
#812000
0'
#813000
b110 0
1'
#814000
0'
#815000
b111 0
1'
#816000
0'
#817000
b1000 0
1'
#818000
0'
#819000
b1001 0
1'
#820000
0'
#821000
b1010 0
1'
#822000
0'
#823000
b1011 0
1'
#824000
0'
#825000
b1100 0
1'
#826000
0'
#827000
b1101 0
1'
#828000
0'
#829000
b1110 0
1'
#830000
0'
#831000
1=
16
1;
14
b11 9
18
b11 2
11
1/
b1111 0
1'
#832000
0'
#833000
06
0=
0;
04
b0 9
08
b0 2
01
1%
1"
0/
b0 0
17
b10 .
b10 3
05
1>
b10 -
b10 :
0<
1'
#834000
0'
#835000
b1 0
1'
#836000
0'
#837000
b10 0
1'
#838000
0'
#839000
b11 0
1'
#840000
0'
#841000
b100 0
1'
#842000
0'
#843000
b101 0
1'
#844000
0'
#845000
b110 0
1'
#846000
0'
#847000
b111 0
1'
#848000
0'
#849000
b1000 0
1'
#850000
0'
#851000
b1001 0
1'
#852000
0'
#853000
b1010 0
1'
#854000
0'
#855000
b1011 0
1'
#856000
0'
#857000
b1100 0
1'
#858000
0'
#859000
b1101 0
1'
#860000
0'
#861000
b1110 0
1'
#862000
0'
#863000
1;
14
b1 9
18
b1 2
11
1/
b1111 0
1'
#864000
0'
#865000
0;
04
1$
1!
b0 9
08
b0 2
01
0/
b0 0
b11 .
b11 3
15
b11 -
b11 :
1<
1'
#866000
0'
#867000
b1 0
1'
#868000
0'
#869000
b10 0
1'
#870000
0'
#871000
b11 0
1'
#872000
0'
#873000
b100 0
1'
#874000
0'
#875000
b101 0
1'
#876000
0'
#877000
b110 0
1'
#878000
0'
#879000
b111 0
1'
#880000
0'
#881000
b1000 0
1'
#882000
0'
#883000
b1001 0
1'
#884000
0'
#885000
b1010 0
1'
#886000
0'
#887000
b1011 0
1'
#888000
0'
#889000
b1100 0
1'
#890000
0'
#891000
b1101 0
1'
#892000
0'
#893000
b1110 0
1'
#894000
0'
#895000
1=
16
1;
14
b11 9
18
b11 2
11
1/
b1111 0
1'
#896000
0'
#897000
06
0=
0;
04
0$
0&
0!
0#
b0 9
08
b0 2
01
0%
0"
0/
b0 0
07
b0 .
b0 3
05
0>
b0 -
b0 :
0<
1'
#898000
0'
#899000
b1 0
1'
#900000
0'
#901000
b10 0
1'
#902000
0'
#903000
b11 0
1'
#904000
0'
#905000
b100 0
1'
#906000
0'
#907000
b101 0
1'
#908000
0'
#909000
b110 0
1'
#910000
0'
#911000
b111 0
1'
#912000
0'
#913000
b1000 0
1'
#914000
0'
#915000
b1001 0
1'
#916000
0'
#917000
b1010 0
1'
#918000
0'
#919000
b1011 0
1'
#920000
0'
#921000
b1100 0
1'
#922000
0'
#923000
b1101 0
1'
#924000
0'
#925000
b1110 0
1'
#926000
0'
#927000
1;
14
b1 9
18
b1 2
11
1/
b1111 0
1'
#928000
0'
#929000
0;
04
1&
1#
b0 9
08
b0 2
01
0/
b0 0
b1 .
b1 3
15
b1 -
b1 :
1<
1'
#930000
0'
#931000
b1 0
1'
#932000
0'
#933000
b10 0
1'
#934000
0'
#935000
b11 0
1'
#936000
0'
#937000
b100 0
1'
#938000
0'
#939000
b101 0
1'
#940000
0'
#941000
b110 0
1'
#942000
0'
#943000
b111 0
1'
#944000
0'
#945000
b1000 0
1'
#946000
0'
#947000
b1001 0
1'
#948000
0'
#949000
b1010 0
1'
#950000
0'
#951000
b1011 0
1'
#952000
0'
#953000
b1100 0
1'
#954000
0'
#955000
b1101 0
1'
#956000
0'
#957000
b1110 0
1'
#958000
0'
#959000
1=
16
1;
14
b11 9
18
b11 2
11
1/
b1111 0
1'
#960000
0'
#961000
06
0=
0;
04
b0 9
08
b0 2
01
1%
1"
0/
b0 0
17
b10 .
b10 3
05
1>
b10 -
b10 :
0<
1'
#962000
0'
#963000
b1 0
1'
#964000
0'
#965000
b10 0
1'
#966000
0'
#967000
b11 0
1'
#968000
0'
#969000
b100 0
1'
#970000
0'
#971000
b101 0
1'
#972000
0'
#973000
b110 0
1'
#974000
0'
#975000
b111 0
1'
#976000
0'
#977000
b1000 0
1'
#978000
0'
#979000
b1001 0
1'
#980000
0'
#981000
b1010 0
1'
#982000
0'
#983000
b1011 0
1'
#984000
0'
#985000
b1100 0
1'
#986000
0'
#987000
b1101 0
1'
#988000
0'
#989000
b1110 0
1'
#990000
0'
#991000
1;
14
b1 9
18
b1 2
11
1/
b1111 0
1'
#992000
0'
